pycrowdsec/__init__.py
pycrowdsec/cache.py
pycrowdsec/client.py
pycrowdsec/utils.py
pycrowdsec/django/__init__.py
pycrowdsec/flask/__init__.py
pycrowdsec-0.0.5.dist-info/LICENSE
pycrowdsec-0.0.5.dist-info/METADATA
pycrowdsec-0.0.5.dist-info/WHEEL
pycrowdsec-0.0.5.dist-info/top_level.txt
pycrowdsec-0.0.5.dist-info/RECORD
