Metadata-Version: 2.1
Name: pycrowdsec
Version: 0.0.5
Summary: Python bouncer and clients for crowdsec
Home-page: https://github.com/crowdsecurity/pycrowdsec
Author: CrowdSec
Author-email: core.tech@crowdsec.net
Project-URL: Bug Tracker, https://github.com/crowdsecurity/pycrowdsec/issues
Classifier: Programming Language :: Python :: 3
Classifier: Operating System :: OS Independent
Classifier: License :: OSI Approved :: MIT License
Requires-Python: >=3.7
License-File: LICENSE
Requires-Dist: requests
Requires-Dist: importlib-metadata
Provides-Extra: geo
Requires-Dist: geoip2 ; extra == 'geo'
